diego_utils/__init__.py
diego_utils/metrics/__init__.py
diego_utils/metrics/distributions.py
diego_utils-0.1.0.dist-info/LICENSE
diego_utils-0.1.0.dist-info/METADATA
diego_utils-0.1.0.dist-info/WHEEL
diego_utils-0.1.0.dist-info/top_level.txt
diego_utils-0.1.0.dist-info/RECORD
